dsspkg/__init__.py
dsspkg/data_scaling_split.py
dsspkg/dss.py
dsspkg/dss_p.py
dsspkg/sth/minus.pkl
dsspkg/sth/minus_p.pkl
dsspkg/sth/radio.pkl
dsspkg/sth/radio_p.pkl
dsspkg-0.3.3.dist-info/LICENSE
dsspkg-0.3.3.dist-info/METADATA
dsspkg-0.3.3.dist-info/WHEEL
dsspkg-0.3.3.dist-info/top_level.txt
dsspkg-0.3.3.dist-info/RECORD
