Metadata-Version: 2.1
Name: dsspkg
Version: 0.3.3
Summary: A data splitting and scaling package
Author: DW
Author-email: prwe98@gmail.com
Requires-Python: >=3.10
License-File: LICENSE
